[
  {
    "id": "q_sim_0203_01",
    "standard_id": "12정02-03",
    "교과": "정보",
    "단원": "",
    "내용영역": "Ⅱ-3. 빅데이터 수집",
    "성취기준명": "빅데이터의 개념과 특징에 대한 이해를 바탕으로, 문제 해결에 적합한 데이터를 수집한다.",
    "유형": "5지선다형",
    "문제": "빅데이터의 3V 특징으로 옳은 것은?",
    "코드": null,
    "언어": null,
    "실행결과": null,
    "표": null,
    "이미지": null,
    "선택지": {
      "1": "양(Volume), 속도(Velocity), 다양성(Variety)",
      "2": "양(Volume), 정확성(Veracity), 가치(Value)",
      "3": "속도(Velocity), 다양성(Variety), 신뢰성(Reliability)",
      "4": "양(Volume), 다양성(Variety), 보안성(Security)",
      "5": "가치(Value), 정확성(Veracity), 다양성(Variety)"
    },
    "정답": 1,
    "해설": "빅데이터는 데이터의 양(Volume), 생성 속도(Velocity), 형태의 다양성(Variety) 세 가지 특징을 가지며 이를 3V라고 한다.",
    "유사문제": true,
    "AI생성": true
  },
  {
    "id": "q_sim_0203_02",
    "standard_id": "12정02-03",
    "교과": "정보",
    "단원": "",
    "내용영역": "Ⅱ-3. 빅데이터 수집",
    "성취기준명": "빅데이터의 개념과 특징에 대한 이해를 바탕으로, 문제 해결에 적합한 데이터를 수집한다.",
    "유형": "5지선다형",
    "문제": "빅데이터의 특징 중 다음 설명에 해당하는 것으로 옳은 것은?",
    "코드": null,
    "언어": null,
    "실행결과": null,
    "표": "| 설명 |\n| :--- |\n| 데이터베이스처럼 구조화된 데이터와 이메일, SNS 게시물처럼 구조화되지 않은 데이터 등 여러 형태로 데이터가 존재한다 |",
    "이미지": null,
    "선택지": {
      "1": "양(Volume)",
      "2": "속도(Velocity)",
      "3": "다양성(Variety)",
      "4": "가치(Value)",
      "5": "정확성(Veracity)"
    },
    "정답": 3,
    "해설": "다양성(Variety)은 구조화된 데이터와 구조화되지 않은 데이터 등 다양한 형태로 데이터가 존재한다는 특징이다.",
    "유사문제": true,
    "AI생성": true
  },
  {
    "id": "q_sim_0203_03",
    "standard_id": "12정02-03",
    "교과": "정보",
    "단원": "",
    "내용영역": "Ⅱ-3. 빅데이터 수집",
    "성취기준명": "빅데이터의 개념과 특징에 대한 이해를 바탕으로, 문제 해결에 적합한 데이터를 수집한다.",
    "유형": "5지선다형",
    "문제": "빅데이터의 개념에 대한 설명으로 옳은 것은?",
    "코드": null,
    "언어": null,
    "실행결과": null,
    "표": null,
    "이미지": null,
    "선택지": {
      "1": "빅데이터는 기존의 관리 방법이나 분석 체계로 처리하기 어려운 막대한 양의 데이터셋 또는 그것을 처리하는 기술을 의미한다.",
      "2": "빅데이터는 반드시 정형 데이터로만 이루어져야 한다.",
      "3": "빅데이터는 개인 정보만을 대상으로 하는 데이터이다.",
      "4": "빅데이터는 항상 실시간으로만 수집되는 데이터를 의미한다.",
      "5": "빅데이터는 데이터의 양이 1GB를 넘는 모든 데이터를 가리킨다."
    },
    "정답": 1,
    "해설": "빅데이터는 기존의 관리 방법이나 분석 체계로는 처리하기 어려운 막대한 양의 데이터셋, 또는 그것을 처리하는 기술을 의미한다. 정형·비정형 데이터를 모두 포함할 수 있다.",
    "유사문제": true,
    "AI생성": true
  },
  {
    "id": "q_sim_0203_04",
    "standard_id": "12정02-03",
    "교과": "정보",
    "단원": "",
    "내용영역": "Ⅱ-3. 빅데이터 수집",
    "성취기준명": "빅데이터의 개념과 특징에 대한 이해를 바탕으로, 문제 해결에 적합한 데이터를 수집한다.",
    "유형": "5지선다형",
    "문제": "공공 데이터에 대한 설명으로 옳지 않은 것은?",
    "코드": null,
    "언어": null,
    "실행결과": null,
    "표": null,
    "이미지": null,
    "선택지": {
      "1": "개별 공공 기관이 업무 수행이나 연구 목적으로 생성·수집한 데이터이다.",
      "2": "정부의 업무나 연구 목적으로 사용되기 때문에 신뢰성이 높다.",
      "3": "가장 큰 특징은 개방성으로, 개인 정보 보호와 국가 안보를 위반하지 않는 범위에서 누구나 자유롭게 쓸 수 있다.",
      "4": "공공데이터포털(data.go.kr), 기상자료개방포털(data.kma.go.kr) 등에서 수집할 수 있다.",
      "5": "상업적 목적으로만 생성되며 일반인은 접근할 수 없다."
    },
    "정답": 5,
    "해설": "공공 데이터는 정부의 업무나 연구 목적으로 사용되어 신뢰성이 높고, 개방성이 가장 큰 특징이라 국가 안보 등을 위반하지 않는 범위에서 누구나 자유롭게 쓸 수 있도록 공개되어 있다. 상업적 목적으로만 생성되고 일반인이 접근할 수 없다는 설명은 옳지 않다.",
    "유사문제": true,
    "AI생성": true
  },
  {
    "id": "q_sim_0203_05",
    "standard_id": "12정02-03",
    "교과": "정보",
    "단원": "",
    "내용영역": "Ⅱ-3. 빅데이터 수집",
    "성취기준명": "빅데이터의 개념과 특징에 대한 이해를 바탕으로, 문제 해결에 적합한 데이터를 수집한다.",
    "유형": "5지선다형",
    "문제": "다음이 설명하는 데이터 수집 방법으로 옳은 것은?",
    "코드": null,
    "언어": null,
    "실행결과": null,
    "표": "| 설명 |\n| :--- |\n| 개인이나 기업 등에서 상업적 목적과 업무 효율성 향상을 위해 수집되는 데이터로, 공공 데이터보다 더 전문적이고 활용 가치가 높다. 캐글(kaggle), 데이콘(DACON) 등에서 수집할 수 있다 |",
    "이미지": null,
    "선택지": {
      "1": "공공 데이터",
      "2": "민간 데이터",
      "3": "웹크롤링",
      "4": "직접 수집",
      "5": "정형 데이터"
    },
    "정답": 2,
    "해설": "민간 데이터는 개인이나 기업이 상업적 목적과 업무 효율성 향상을 위해 수집하는 데이터로, 캐글과 데이콘이 대표적인 수집 사이트이다.",
    "유사문제": true,
    "AI생성": true
  },
  {
    "id": "q_sim_0203_06",
    "standard_id": "12정02-03",
    "교과": "정보",
    "단원": "",
    "내용영역": "Ⅱ-3. 빅데이터 수집",
    "성취기준명": "빅데이터의 개념과 특징에 대한 이해를 바탕으로, 문제 해결에 적합한 데이터를 수집한다.",
    "유형": "5지선다형",
    "문제": "웹크롤링(web crawling)에 대한 설명으로 옳은 것은?",
    "코드": null,
    "언어": null,
    "실행결과": null,
    "표": null,
    "이미지": null,
    "선택지": {
      "1": "설문 조사를 통해 데이터를 직접 수집하는 방법이다.",
      "2": "웹 크롤러(web crawler)라는 프로그램으로 웹 사이트의 정보를 조직적·자동화된 방법으로 수집하는 작업이다.",
      "3": "정부 기관에서만 사용할 수 있는 데이터 수집 방법이다.",
      "4": "센서를 이용해 물리적 환경 데이터를 수집하는 방법이다.",
      "5": "카메라로 촬영하여 이미지 데이터를 수집하는 방법이다."
    },
    "정답": 2,
    "해설": "웹 크롤러로 웹 사이트의 정보를 조직적 또는 자동화된 방법으로 수집하는 작업을 웹크롤링이라고 한다. 특정 정보를 자동으로, 최신 상태로 수집할 수 있다는 장점이 있다.",
    "유사문제": true,
    "AI생성": true
  },
  {
    "id": "q_sim_0203_07",
    "standard_id": "12정02-03",
    "교과": "정보",
    "단원": "",
    "내용영역": "Ⅱ-3. 빅데이터 수집",
    "성취기준명": "빅데이터의 개념과 특징에 대한 이해를 바탕으로, 문제 해결에 적합한 데이터를 수집한다.",
    "유형": "5지선다형",
    "문제": "직접 수집 방법에 대한 설명으로 옳지 않은 것은?",
    "코드": null,
    "언어": null,
    "실행결과": null,
    "표": null,
    "이미지": null,
    "선택지": {
      "1": "가공되지 않은 데이터를 조사자가 직접 수집·작성하는 방법이다.",
      "2": "조사자에게 정작 필요한 데이터가 없을 때, 센서나 플랫폼을 활용해 필요한 데이터를 정확하게 얻을 수 있다.",
      "3": "대표적인 방법으로 설문 조사, 카메라를 이용한 이미지 수집, 센서를 이용한 데이터 수집 등이 있다.",
      "4": "과학적 연구나 인공지능 예측에도 활용될 수 있다.",
      "5": "직접 수집은 항상 공공데이터포털을 통해서만 이루어진다."
    },
    "정답": 5,
    "해설": "직접 수집은 조사자가 설문 조사, 카메라, 센서 등을 이용해 데이터를 직접 얻는 방법으로, 공공데이터포털(공공 데이터 수집 경로)과는 무관하다.",
    "유사문제": true,
    "AI생성": true
  },
  {
    "id": "q_sim_0203_08",
    "standard_id": "12정02-03",
    "교과": "정보",
    "단원": "",
    "내용영역": "Ⅱ-3. 빅데이터 수집",
    "성취기준명": "빅데이터의 개념과 특징에 대한 이해를 바탕으로, 문제 해결에 적합한 데이터를 수집한다.",
    "유형": "5지선다형",
    "문제": "빅데이터를 활용한 사례로 옳지 않은 것은?",
    "코드": null,
    "언어": null,
    "실행결과": null,
    "표": null,
    "이미지": null,
    "선택지": {
      "1": "은행이 고객의 금융 활동 데이터를 기반으로 맞춤형 금융 상품을 추천한다.",
      "2": "SNS나 동영상 플랫폼이 사용자의 관심사에 맞춘 광고·콘텐츠를 추천한다.",
      "3": "빅데이터는 의료, 금융, 마케팅, 운송 등 다양한 분야에서 활용된다.",
      "4": "빅데이터를 도구와 기술로 분석하면 더 나은 결정을 내리거나 문제를 개선하는 데 도움을 받을 수 있다.",
      "5": "빅데이터는 개인정보 보호를 위해 어떤 분야에서도 실제 서비스에는 활용되지 않는다."
    },
    "정답": 5,
    "해설": "빅데이터는 은행의 고객 맞춤 금융 상품 추천, SNS·동영상 플랫폼의 맞춤 추천 서비스 등 실제로 다양한 분야에서 활용되고 있다.",
    "유사문제": true,
    "AI생성": true
  },
  {
    "id": "q_sim_0203_09",
    "standard_id": "12정02-03",
    "교과": "정보",
    "단원": "",
    "내용영역": "Ⅱ-3. 빅데이터 수집",
    "성취기준명": "빅데이터의 개념과 특징에 대한 이해를 바탕으로, 문제 해결에 적합한 데이터를 수집한다.",
    "유형": "5지선다형",
    "문제": "빅데이터 용량 단위를 작은 것부터 큰 순서로 옳게 나열한 것은?",
    "코드": null,
    "언어": null,
    "실행결과": null,
    "표": null,
    "이미지": null,
    "선택지": {
      "1": "테라바이트(TB) - 페타바이트(PB)",
      "2": "페타바이트(PB) - 테라바이트(TB)",
      "3": "기가바이트(GB) - 페타바이트(PB) - 테라바이트(TB)",
      "4": "페타바이트(PB) - 기가바이트(GB) - 테라바이트(TB)",
      "5": "테라바이트(TB) - 기가바이트(GB) - 페타바이트(PB)"
    },
    "정답": 1,
    "해설": "빅데이터는 데이터 집합의 크기가 테라바이트(TB)에서 페타바이트(PB, 1,024TB)에 이를 만큼 매우 크다. 즉 페타바이트가 테라바이트보다 큰 단위이다.",
    "유사문제": true,
    "AI생성": true
  },
  {
    "id": "q_sim_0203_10",
    "standard_id": "12정02-03",
    "교과": "정보",
    "단원": "",
    "내용영역": "Ⅱ-3. 빅데이터 수집",
    "성취기준명": "빅데이터의 개념과 특징에 대한 이해를 바탕으로, 문제 해결에 적합한 데이터를 수집한다.",
    "유형": "5지선다형",
    "문제": "문제 해결에 필요한 데이터를 수집하는 방법 중, 수집 주체와 방법의 연결이 옳지 않은 것은?",
    "코드": null,
    "언어": null,
    "실행결과": null,
    "표": null,
    "이미지": null,
    "선택지": {
      "1": "공공 데이터 — 공공 기관이 업무·연구 목적으로 생성·수집",
      "2": "민간 데이터 — 개인·기업이 상업적 목적으로 생성·수집",
      "3": "웹크롤링 — 웹 크롤러 프로그램으로 자동 수집",
      "4": "직접 수집 — 설문 조사, 센서, 카메라 등으로 조사자가 직접 수집",
      "5": "웹크롤링 — 은행 창구 태블릿에서 고객이 직접 입력한 데이터 수집"
    },
    "정답": 5,
    "해설": "은행 창구 태블릿에서 고객이 나이·성별·소득 등을 직접 입력하는 것은 웹크롤링(자동화된 웹 정보 수집)이 아니라 직접 수집에 해당한다.",
    "유사문제": true,
    "AI생성": true
  }
]
