[
  {
    "id": "q_digital_0602_01",
    "standard_id": "디논 06-02",
    "교과": "디지털 논리회로",
    "단원": "6. 순서 논리 회로 설계",
    "내용영역": "Ⅵ-2. 저장 요소(플립플롭, 래치)",
    "성취기준명": "래치와 플립플롭의 개념과 동작 원리를 설명할 수 있다.",
    "유형": "5지선다형",
    "문제": "NOR 게이트로 구성한 RS 래치에서 R=1, S=1이 입력을 금지하는 이유로 옳은 것은?",
    "코드": null,
    "언어": null,
    "실행결과": null,
    "표": null,
    "이미지": null,
    "선택지": {
      "1": "출력 Q와 Q̅가 모두 0이 되어 서로 반대여야 할 두 출력이 같아지기 때문이다.",
      "2": "출력 Q와 Q̅가 모두 1이 되어 서로 반대여야 할 두 출력이 같아지기 때문이다.",
      "3": "출력이 이전 상태를 그대로 유지해 버리기 때문이다.",
      "4": "회로에 전류가 흐르지 않기 때문이다.",
      "5": "게이트가 물리적으로 파손되기 때문이다."
    },
    "정답": 1,
    "해설": "NOR 게이트 RS 래치에서 R=S=1이면 두 NOR 게이트의 출력이 모두 0이 되어 Q와 Q̅가 모두 0이 되는 모순이 발생하므로 사용을 금지한다.",
    "AI생성": true
  },
  {
    "id": "q_digital_0602_02",
    "standard_id": "디논 06-02",
    "교과": "디지털 논리회로",
    "단원": "6. 순서 논리 회로 설계",
    "내용영역": "Ⅵ-2. 저장 요소(플립플롭, 래치)",
    "성취기준명": "래치와 플립플롭의 개념과 동작 원리를 설명할 수 있다.",
    "유형": "5지선다형",
    "문제": "래치(latch)와 플립플롭(flip-flop)의 차이로 가장 옳은 것은?",
    "코드": null,
    "언어": null,
    "실행결과": null,
    "표": null,
    "이미지": null,
    "선택지": {
      "1": "래치는 2비트, 플립플롭은 1비트를 저장한다.",
      "2": "래치는 클록 펄스 없이 작동하고, 플립플롭은 클록 펄스를 받아 작동한다.",
      "3": "래치는 조합 논리 회로이고, 플립플롭은 순서 논리 회로이다.",
      "4": "래치는 되먹임 구조가 없고, 플립플롭은 되먹임 구조가 있다.",
      "5": "둘은 이름만 다를 뿐 완전히 동일한 회로이다."
    },
    "정답": 2,
    "해설": "RS 래치는 클록 펄스의 입력 없이 R, S 값에 따라 바로 작동하지만, 클록형 RS 래치(RS 플립플롭)는 클록 펄스가 변화할 때만 출력이 바뀐다.",
    "AI생성": true
  },
  {
    "id": "q_digital_0602_03",
    "standard_id": "디논 06-02",
    "교과": "디지털 논리회로",
    "단원": "6. 순서 논리 회로 설계",
    "내용영역": "Ⅵ-2. 저장 요소(플립플롭, 래치)",
    "성취기준명": "래치와 플립플롭의 개념과 동작 원리를 설명할 수 있다.",
    "유형": "5지선다형",
    "문제": "플립플롭의 특성으로 옳지 않은 것은?",
    "코드": null,
    "언어": null,
    "실행결과": null,
    "표": null,
    "이미지": null,
    "선택지": {
      "1": "1비트의 정보를 저장할 수 있는 기억 회로이다.",
      "2": "입력 신호가 상태 변환을 일으키기 전까지는 원래의 상태를 그대로 유지한다.",
      "3": "클록 펄스(CP)라는 제어 입력을 가진다.",
      "4": "정상 출력(Q)과 보수화된 출력(Q̅)을 가진다.",
      "5": "논리 게이트 없이 저항과 커패시터만으로 구성된다."
    },
    "정답": 5,
    "해설": "플립플롭은 순서 논리 회로의 대표적인 기억 소자로, 논리 게이트의 조합(예: NOR 게이트 2개 또는 NAND 게이트 2개)으로 구성되어 있다.",
    "AI생성": true
  },
  {
    "id": "q_digital_0602_04",
    "standard_id": "디논 06-02",
    "교과": "디지털 논리회로",
    "단원": "6. 순서 논리 회로 설계",
    "내용영역": "Ⅵ-2. 저장 요소(플립플롭, 래치)",
    "성취기준명": "래치와 플립플롭의 개념과 동작 원리를 설명할 수 있다.",
    "유형": "5지선다형",
    "문제": "NAND 게이트로 구성한 RS 래치에서 S̅=0, R̅=1이 입력되었을 때 출력 Q의 상태로 옳은 것은?",
    "코드": null,
    "언어": null,
    "실행결과": null,
    "표": null,
    "이미지": null,
    "선택지": {
      "1": "항상 0으로 리셋된다.",
      "2": "항상 1로 세트된다.",
      "3": "이전 상태를 그대로 유지한다.",
      "4": "사용이 금지된 입력이다.",
      "5": "무작위 값이 출력된다."
    },
    "정답": 2,
    "해설": "NAND 게이트 RS 래치에서 S̅=0이 입력되는 NAND 게이트 출력은 무조건 1이 되어 출력 Q가 항상 1로 세트된다.",
    "AI생성": true
  }
]
