{
  "standard_id": "12인기01-03",
  "title": "맹목적 탐색: 깊이 우선 탐색과 너비 우선 탐색",
  "성취기준명": "맹목적 탐색과 정보 이용 탐색의 차이를 중심으로 지능적 탐색의 원리를 파악한다.",
  "단원": "1. 인공지능의 이해",
  "sections": [
    {
      "heading": "탐색의 두 갈래: 맹목적 탐색과 정보 이용 탐색",
      "content": "그래프 탐색에서는 출발 노드로부터 시작하여 정해진 순서대로 노드를 확장하는 과정에서 목표 노드를 찾아내는 방법으로 문제를 해결한다. 탐색 과정에서 상태 공간에 관한 정보를 사용하는지 여부에 따라 탐색은 두 갈래로 나뉜다.\n\n- 맹목적 탐색(blind search, 무정보 탐색): 상태 공간에 관한 정보 없이 모든 상태를 규칙에 따라 탐색하는 방법으로, 분기점에서 갈 방향을 미리 정해 둔다. 대표적으로 깊이 우선 탐색과 너비 우선 탐색이 있다.\n- 정보 이용 탐색(informed search, 휴리스틱 탐색·경험적 탐색): 상태 공간에 관한 정보를 활용하여 지능적으로 그래프의 일부만 효과적으로 탐색함으로써 가까운 근삿값을 빨리 찾는 방법이다. 대표적으로 언덕 등반 탐색, 최상 우선 탐색, A* 알고리즘이 있다. 정보 이용 탐색이 항상 옳은 답을 주는 것은 아니지만, 대부분의 경우에 잘 맞는 정보를 제공해 효율적인 탐색을 가능하게 한다.\n\n이 자료에서는 먼저 맹목적 탐색(깊이 우선 탐색, 너비 우선 탐색)을 자세히 살펴본다."
    },
    {
      "heading": "깊이 우선 탐색(DFS)",
      "content": "깊이 우선 탐색(DFS: Depth First Search)은 탐색 트리에서 갈 수 있는 길이 있는 한 앞으로 계속 전진하여 탐색하는 방법이다. 분기점에 도착했을 때 방문하지 않은 곳을 선택해 앞으로 나아가는 과정을 반복하며 목표에 도달한다. 만약 막다른 길에 다다르거나 길이 없는 경우에는 이전 상태 중 다른 경로로 갈 수 있는 분기점까지 되돌아가 다시 탐색한다(이때 분기점에서 어느 방향으로 갈지는 미리 정해 두어야 한다).\n\n루트 노드가 A이고 A의 자식이 B, C, D / B의 자식이 E / C의 자식이 F / D의 자식이 G, H / E의 자식이 I, J / H의 자식이 K인 트리가 있다고 하자. A부터 시작해 자식 노드 중 하나(B)를 골라 더 깊게 들어가 E, I까지 내려간 뒤 더 갈 곳이 없으면 E로 돌아와 J를 탐색하고, 이런 식으로 모든 노드의 끝까지 계속 깊게 들어가며 탐색하면 다음과 같은 순서가 된다.\n\n탐색 경로: A → B → E → I → J → C → F → D → G → H → K\n\n깊이 우선 탐색은 '강 건너기 문제'(농부가 양·늑대·양배추를 배로 한 번에 하나씩만 실어 나르며 무사히 강을 건너는 문제, 규칙: 양과 늑대만 남으면 늑대가 양을 먹고, 양과 양배추만 남으면 양이 양배추를 먹는다)에도 적용할 수 있다. 미로 탐색에도 적용할 수 있는데, 미로가 갈라질 때마다 한쪽을 선택해 더 깊숙이 들어가는 방식이기 때문에 미로의 입구에서 출구를 찾아 나갈 때 쉽게 탐색할 수 있다. 다만 깊이 우선 탐색은 깊이가 깊은 해답을 가진 구조나 해답이 없는 깊은 경로를 탐색하는 경우에는 빠져나오지 못할 수 있다는 한계가 있다."
    },
    {
      "heading": "너비 우선 탐색(BFS)",
      "content": "너비 우선 탐색(BFS: Breadth First Search)은 탐색 트리를 넓고 얇게 탐색하는 방법이다. 트리를 탐색하다 분기점에 도착했을 때, 분기점과 연결된 동일한 깊이의 상태 공간을 모두 탐색한 후 다음 단계로 나아간다. 목표 지점에 도착할 때까지 가로 방향으로 나아가며, 방문한 적이 있는 분기점은 재방문하지 않는다. 즉 첫 번째 수에서 가능한 모든 것을 확인한 후, 두 번째 수에서도 모든 것을 확인하며 한 수 한 수 전부 확인하면서 천천히 깊어진다.\n\n깊이 우선 탐색과 같은 트리(A의 자식 B,C,D / B의 자식 E / C의 자식 F / D의 자식 G,H / E의 자식 I,J / H의 자식 K)를 너비 우선 탐색으로 탐색하면, A에서 자식 노드 B, C, D를 먼저 모두 탐색한 후 E, F, G, H를 탐색하고, 마지막으로 I, J, K를 탐색한다.\n\n탐색 경로: A → B → C → D → E → F → G → H → I → J → K\n\n너비 우선 탐색은 한 층을 내려가기 전에 그 층에 있는 모든 노드를 방문하기 때문에, 웹 크롤러가 웹 페이지를 탐색할 때 활용된다 — 특정 웹 페이지에 접속한 후 그 페이지에 있는 모든 링크를 확인하고, 다시 그중 첫 링크 사이트로 가서 그 페이지의 모든 링크를 검색하는 방식이다.\n\n트리 탐색에서는 깊이 우선 탐색과 너비 우선 탐색에 큰 차이가 없지만, 그래프 탐색에서 목표 상태에 도달하는 경로가 여러 가지일 경우 깊이 우선 탐색은 경우에 따라 더 간단한 경로를 놓치고 복잡한 경로를 제시할 수도 있다."
    },
    {
      "heading": "직접 확인해보기: 같은 트리를 DFS와 BFS로 탐색하기",
      "advanced": true,
      "content": "교과서에 나온 트리(A→B,C,D / B→E / C→F / D→G,H / E→I,J / H→K)를 그대로 딕셔너리로 표현하고, 재귀로 구현한 깊이 우선 탐색과 큐(queue)로 구현한 너비 우선 탐색을 각각 실행해 본다. 실행 결과의 탐색 경로가 교과서의 'A→B→E→I→J→C→F→D→G→H→K'(DFS), 'A→B→C→D→E→F→G→H→I→J→K'(BFS)와 정확히 일치하는지 확인해 보자.",
      "code": "tree = {\n    'A': ['B', 'C', 'D'],\n    'B': ['E'],\n    'C': ['F'],\n    'D': ['G', 'H'],\n    'E': ['I', 'J'],\n    'F': [], 'G': [], 'I': [], 'J': [], 'K': [],\n    'H': ['K'],\n}\n\ndef dfs(node, visited=None):\n    if visited is None:\n        visited = []\n    visited.append(node)\n    for child in tree.get(node, []):\n        dfs(child, visited)\n    return visited\n\ndef bfs(start):\n    from collections import deque\n    visited = []\n    queue = deque([start])\n    seen = {start}\n    while queue:\n        node = queue.popleft()\n        visited.append(node)\n        for child in tree.get(node, []):\n            if child not in seen:\n                seen.add(child)\n                queue.append(child)\n    return visited\n\nprint(\"DFS:\", ' → '.join(dfs('A')))\nprint(\"BFS:\", ' → '.join(bfs('A')))\n"
    },
    {
      "heading": "정리: 맹목적 탐색의 두 방법 비교",
      "content": "깊이 우선 탐색과 너비 우선 탐색은 둘 다 상태 공간에 대한 사전 정보 없이 정해진 규칙(방향)에 따라 기계적으로 모든 상태를 탐색한다는 공통점이 있다. 차이는 '어느 방향으로 먼저 넓게/깊게 갈 것인가'에 있다 — 깊이 우선 탐색은 한 방향으로 끝까지 가 본 뒤 되돌아오고, 너비 우선 탐색은 같은 깊이를 모두 살펴본 뒤 다음 깊이로 넘어간다. 다음 자료에서는 상태 공간에 관한 정보(휴리스틱)를 활용해 더 효율적으로 탐색하는 정보 이용 탐색(언덕 등반 탐색, 최상 우선 탐색, A* 알고리즘)을 살펴본다."
    }
  ]
}
